odoo/addons/l10n_br_nfe/README.rst
odoo/addons/l10n_br_nfe/__init__.py
odoo/addons/l10n_br_nfe/__manifest__.py
odoo/addons/l10n_br_nfe/hooks.py
odoo/addons/l10n_br_nfe/constants/mde.py
odoo/addons/l10n_br_nfe/constants/nfe.py
odoo/addons/l10n_br_nfe/data/ir_config_parameter.xml
odoo/addons/l10n_br_nfe/demo/company_demo.xml
odoo/addons/l10n_br_nfe/demo/fiscal_document_demo.xml
odoo/addons/l10n_br_nfe/demo/res_users_demo.xml
odoo/addons/l10n_br_nfe/i18n/l10n_br_nfe.pot
odoo/addons/l10n_br_nfe/i18n/pt_BR.po
odoo/addons/l10n_br_nfe/models/__init__.py
odoo/addons/l10n_br_nfe/models/cest.py
odoo/addons/l10n_br_nfe/models/cfop.py
odoo/addons/l10n_br_nfe/models/dfe.py
odoo/addons/l10n_br_nfe/models/document.py
odoo/addons/l10n_br_nfe/models/document_line.py
odoo/addons/l10n_br_nfe/models/document_related.py
odoo/addons/l10n_br_nfe/models/document_supplement.py
odoo/addons/l10n_br_nfe/models/document_type.py
odoo/addons/l10n_br_nfe/models/invalidate_number.py
odoo/addons/l10n_br_nfe/models/mde.py
odoo/addons/l10n_br_nfe/models/ncm.py
odoo/addons/l10n_br_nfe/models/product_product.py
odoo/addons/l10n_br_nfe/models/product_supplierinfo.py
odoo/addons/l10n_br_nfe/models/res_city.py
odoo/addons/l10n_br_nfe/models/res_company.py
odoo/addons/l10n_br_nfe/models/res_config_settings.py
odoo/addons/l10n_br_nfe/models/res_country.py
odoo/addons/l10n_br_nfe/models/res_country_state.py
odoo/addons/l10n_br_nfe/models/res_partner.py
odoo/addons/l10n_br_nfe/models/tax_ipi_guideline.py
odoo/addons/l10n_br_nfe/models/uom.py
odoo/addons/l10n_br_nfe/readme/CONFIGURE.md
odoo/addons/l10n_br_nfe/readme/CONTRIBUTORS.md
odoo/addons/l10n_br_nfe/readme/DESCRIPTION.md
odoo/addons/l10n_br_nfe/readme/INSTALL.md
odoo/addons/l10n_br_nfe/readme/ROADMAP.md
odoo/addons/l10n_br_nfe/readme/USAGE.md
odoo/addons/l10n_br_nfe/report/__init__.py
odoo/addons/l10n_br_nfe/report/danfe_nfce.xml
odoo/addons/l10n_br_nfe/report/danfe_report.xml
odoo/addons/l10n_br_nfe/report/ir_actions_report.py
odoo_addon_l10n_br_nfe-17.0.5.0.0.1.dist-info/METADATA
odoo_addon_l10n_br_nfe-17.0.5.0.0.1.dist-info/WHEEL
odoo_addon_l10n_br_nfe-17.0.5.0.0.1.dist-info/top_level.txt
odoo_addon_l10n_br_nfe-17.0.5.0.0.1.dist-info/RECORD
