Metadata-Version: 2.1
Name: odoo-addon-l10n_br_nfe
Version: 17.0.5.0.0.1
Requires-Python: >=3.10
Requires-Dist: brazilfiscalreport
Requires-Dist: erpbrasil.assinatura
Requires-Dist: erpbrasil.base
Requires-Dist: erpbrasil.edoc
Requires-Dist: erpbrasil.transmissao
Requires-Dist: nfelib
Requires-Dist: odoo-addon-l10n_br_fiscal_certificate>=17.0dev,<17.1dev
Requires-Dist: odoo-addon-l10n_br_fiscal_dfe>=17.0dev,<17.1dev
Requires-Dist: odoo-addon-l10n_br_fiscal_edi>=17.0dev,<17.1dev
Requires-Dist: odoo-addon-l10n_br_nfe_spec>=17.0dev,<17.1dev
Requires-Dist: odoo-addon-spec_driven_model>=17.0dev,<17.1dev
Requires-Dist: odoo>=17.0a,<17.1dev
Summary: Eletronic Invoicing for Brazil / NF-e
Home-page: https://github.com/OCA/l10n-brazil
License: AGPL-3
Author: Akretion, KMEE, Odoo Community Association (OCA)
Author-email: support@odoo-community.org
Classifier: Programming Language :: Python
Classifier: Framework :: Odoo
Classifier: Framework :: Odoo :: 17.0
Classifier: License :: OSI Approved :: GNU Affero General Public License v3
Classifier: Development Status :: 4 - Beta
